odoo/addons/l10n_es_dua_sii/README.rst
odoo/addons/l10n_es_dua_sii/__init__.py
odoo/addons/l10n_es_dua_sii/__manifest__.py
odoo/addons/l10n_es_dua_sii/data/tax_code_map_dua_sii_data.xml
odoo/addons/l10n_es_dua_sii/i18n/bg.po
odoo/addons/l10n_es_dua_sii/i18n/ca.po
odoo/addons/l10n_es_dua_sii/i18n/cs.po
odoo/addons/l10n_es_dua_sii/i18n/es.po
odoo/addons/l10n_es_dua_sii/i18n/es_CR.po
odoo/addons/l10n_es_dua_sii/i18n/fr.po
odoo/addons/l10n_es_dua_sii/i18n/gl.po
odoo/addons/l10n_es_dua_sii/i18n/hr.po
odoo/addons/l10n_es_dua_sii/i18n/l10n_es_dua_sii.pot
odoo/addons/l10n_es_dua_sii/i18n/nl.po
odoo/addons/l10n_es_dua_sii/i18n/pl.po
odoo/addons/l10n_es_dua_sii/i18n/pt.po
odoo/addons/l10n_es_dua_sii/i18n/pt_BR.po
odoo/addons/l10n_es_dua_sii/i18n/ru.po
odoo/addons/l10n_es_dua_sii/i18n/sl.po
odoo/addons/l10n_es_dua_sii/i18n/sv.po
odoo/addons/l10n_es_dua_sii/i18n/tr.po
odoo/addons/l10n_es_dua_sii/models/__init__.py
odoo/addons/l10n_es_dua_sii/models/account_move.py
odoo/addons/l10n_es_dua_sii/readme/CONFIGURATION.rst
odoo/addons/l10n_es_dua_sii/readme/CONTRIBUTORS.rst
odoo/addons/l10n_es_dua_sii/readme/DESCRIPTION.rst
odoo/addons/l10n_es_dua_sii/readme/ROADMAP.rst
odoo/addons/l10n_es_dua_sii/readme/USAGE.rst
odoo/addons/l10n_es_dua_sii/static/description/icon.png
odoo/addons/l10n_es_dua_sii/static/description/index.html
odoo/addons/l10n_es_dua_sii/tests/__init__.py
odoo/addons/l10n_es_dua_sii/tests/test_dua_sii.py
odoo/addons/l10n_es_dua_sii/tests/json/sii_in_invoice_p_iva10_bc_dict.json
odoo/addons/l10n_es_dua_sii/tests/json/sii_in_invoice_p_iva21_ibc_dict.json
odoo_addon_l10n_es_dua_sii-16.0.2.0.0.dist-info/METADATA
odoo_addon_l10n_es_dua_sii-16.0.2.0.0.dist-info/WHEEL
odoo_addon_l10n_es_dua_sii-16.0.2.0.0.dist-info/top_level.txt
odoo_addon_l10n_es_dua_sii-16.0.2.0.0.dist-info/RECORD
